<?xml version="1.0" encoding="UTF-8"?>
<odoo>
    <template id="assets_backend" name="web_widget_fonticonpicker assets" inherit_id="web.assets_backend">
        <xpath expr="." position="inside">
            <link rel="stylesheet" type="text/css" href="/web_widget_fonticonpicker/static/src/lib/fontawesome-iconpicker/css/fontawesome-iconpicker.min.css"/>
            <script type="text/javascript" src="/web_widget_fonticonpicker/static/src/lib/fontawesome-iconpicker/js/fontawesome-iconpicker.min.js"></script>
            <script type="text/javascript" src="/web_widget_fonticonpicker/static/src/js/widget.js"></script>
            <style>
                .btn-group.open .dropdown-toggle { background-color: #999 !important; }
            </style>
        </xpath>
    </template>
</odoo>
